kgbench/__init__.py
kgbench/load.py
kgbench/parse.py
kgbench/urls.py
kgbench/util.py
kgbench_loader-0.2.0.dist-info/licenses/LICENSE
kgbench_loader-0.2.0.dist-info/METADATA
kgbench_loader-0.2.0.dist-info/WHEEL
kgbench_loader-0.2.0.dist-info/top_level.txt
kgbench_loader-0.2.0.dist-info/RECORD
