Metadata-Version: 2.4
Name: kgbench-loader
Version: 0.2.0
Summary: A set of benchmark datasets for knowledge graph node classification
Author: Peter Bloem (Vrije Universiteit), Victor de Boer (Vrije Universiteit), Xander Wilcke (Vrije Universiteit), Lucas van Berkel
Project-URL: Homepage, https://kgbench.info
Requires-Python: >=3.10
License-File: LICENSE
Requires-Dist: fire>=0.7.0
Requires-Dist: numpy>=2.2.6
Requires-Dist: pillow>=11.2.1
Requires-Dist: rdflib>=7.1.4
Requires-Dist: scikit-image>=0.25.2
Requires-Dist: torch>=2.7.1
Requires-Dist: torchvision>=0.22.1
Requires-Dist: wget>=3.2
Dynamic: license-file
